.editorconfig
.travis.yml
AUTHORS.rst
CHANGELOG.rst
CONTRIBUTING.rst
LICENSE
MANIFEST.in
README.rst
requirements.txt
setup.cfg
setup.py
tox.ini
docs/Makefile
docs/authors.rst
docs/changelog.rst
docs/conf.py
docs/contributing.rst
docs/index.rst
docs/make.bat
docs/readme.rst
docs/requirements.txt
requirements/app.txt
requirements/base.txt
requirements/docs.txt
requirements/tests.txt
sails/__init__.py
sails/api.py
sails/clock.py
sails/commands.py
sails/session.py
sails/timestamps.py
sails/playback/__init__.py
sails/playback/basic.py
sails/playback/osc.py
sails/scripts/__init__.py
sails/scripts/console.py
sails/scripts/gui.py
sails/scripts/s4ilsd.py
sails/server/__init__.py
sails/server/control/__init__.py
sails/server/control/pykernel.py
sails/ui/__init__.py
sails/ui/app.py
sails/ui/mainmenubar.py
sails/ui/mainwindow.py
sails/ui/mainwindow.ui
sails/ui/welcomewidget.py
sails/ui/welcomewidget.ui
sails/ui/openers/__init__.py
sails/ui/openers/anyopener.py
sails/ui/openers/opener.py
sails/ui/openers/sunsynthopener.py
sails/ui/openers/sunvoxopener.py
sails/ui/polyphonist/__init__.py
sails/ui/polyphonist/polyphonistmainmenubar.py
sails/ui/polyphonist/polyphonistmainwindow.py
sails/ui/polyphonist/polyphonistmainwindow.ui
sails/ui/settings/__init__.py
sails/ui/settings/audiosettingswidget.py
sails/ui/settings/audiosettingswidget.ui
sails/ui/settings/settingsdialog.py
sails/ui/settings/settingsdialog.ui
sails/ui/settings/sunvoxsettingswidget.py
sails/ui/settings/sunvoxsettingswidget.ui
sails/ui/sun/__init__.py
sails/ui/sun/synth/__init__.py
sails/ui/sun/synth/sunsynthmainmenubar.py
sails/ui/sun/synth/sunsynthmainwindow.py
sails/ui/sun/synth/sunsynthmainwindow.ui
sails/ui/sun/vox/__init__.py
sails/ui/sun/vox/sunvoxmainmenubar.py
sails/ui/sun/vox/sunvoxmainwindow.py
sails/ui/sun/vox/sunvoxmainwindow.ui
solar_sails.egg-info/PKG-INFO
solar_sails.egg-info/SOURCES.txt
solar_sails.egg-info/dependency_links.txt
solar_sails.egg-info/entry_points.txt
solar_sails.egg-info/not-zip-safe
solar_sails.egg-info/requires.txt
solar_sails.egg-info/top_level.txt
specs/gui.spec
tests/__init__.py
tests/test_clock.py
tests/test_timelines.py